dictRysan/__init__.py
dictRysan-1.4.6.dist-info/LICENSE.txt
dictRysan-1.4.6.dist-info/METADATA
dictRysan-1.4.6.dist-info/WHEEL
dictRysan-1.4.6.dist-info/top_level.txt
dictRysan-1.4.6.dist-info/RECORD
