Metadata-Version: 2.1
Name: dictRysan
Version: 1.4.6
Summary: dictionary
Home-page: https://github.com/RafsanJany-44/Python-packages/tree/master/dictRysan/
Author: Rafsan Jany
Author-email: rafsanjany1213@gmail.com
License: UNKNOWN
Platform: UNKNOWN
Classifier: Programming Language :: Python :: 3
Classifier: License :: OSI Approved :: MIT License
Classifier: Operating System :: OS Independent
